{
    "array": [
        {
            "pertanyaan": "<html>Now there's drama (drama), found a club for that. <br>Apa judul lagu dari lirik tersebut?</html>",
            "string1": "Lowkey",
            "string2": "Every Summertime",
            "string3": "Oceans & Engines",
            "string4": "High school in Jakarta",
            "benar": 4
        },
        {
            "pertanyaan": "<html>Melihat tawamu~. Mendengar senandungmu~. <br>Judul lagunya adalah ...</html>",
            "string1": "Anugerah Terindah",
            "string2": "Hari Bersamanya",
            "string3": "Anugrah Terindah yang Pernah Kumiliki",
            "string4": "Buat Aku Tersenyum",
            "benar": 3
        },
        {
            "pertanyaan": "<html>'Bangun pemudi pemuda Indonesia ...' <br>Apa lanjutan lirik lagu ini??</html>",
            "string1": "Lengan Bajumu Singkirkan untuk negara",
            "string2": "Tangan bajumu singkirkan untuk negara",
            "string3": "Lengan bajumu singsingkan untuk negara",
            "string4": "Tangan bajumu singsingkan untuk negara",
            "benar": 4
        },
        {
            "pertanyaan": "<html>Sambung lirik dari 'It's me, <br>hi, i'm the problem, it's me...'</html>",
            "string1": "My bad sign, everybody can see",
            "string2": "At tea time, everybody agrees",
            "string3": "At all times",
            "string4": "I'll make time, everybody agrees",
            "benar": 2
        },
        {
            "pertanyaan": "<html>Lagu 'Blue Bird' pada opening<br>Naruto Shippuden dibawakan oleh ?</html>",
            "string1": "Kana-Boon",
            "string2": "Ikimono Gakari",
            "string3": "Daisuke",
            "string4": "PelleK",
            "benar": 2
        },
        {
            "pertanyaan": "<html>Siapakah pencipta lagu legendaris <br>Indonesia 'Bengawan Solo'?</html>",
            "string1": "Titiek Puspa",
            "string2": "Denny Caknan",
            "string3": "NDX",
            "string4": "Gesang",
            "benar": 4
        },
        {
            "pertanyaan": "<html>Potongan lirik yang benar dari <br>hymne/mars UNS adalah..</html>",
            "string1": "Rasa teguh dalam hati",
            "string2": "Diluhurkanlah namamu",
            "string3": "Untuk negeri tercinta",
            "string4": "Biru hijau kampusku",
            "benar": 2
        },
        {
            "pertanyaan": "<html>'And I swear that everyday <br>you'll get better'. <br>Judul lagu ini adalah</html>",
            "string1": "I knew I Love You",
            "string2": "I Met You In The Dark",
            "string3": "Say You Won't Let Go",
            "string4": "Say Something",
            "benar": 3
        },
        {
            "pertanyaan": "<html>Siapa penyanyi lagu '<br>Jiwa yang Bersedih'?</html>",
            "string1": "Gea Indrawati",
            "string2": "Ghea Indrawari",
            "string3": "Gea Indrawari",
            "string4": "Ghea Indrawari",
            "benar": 4
        },
        {
            "pertanyaan": "<html>'Tebak judul lagu indonesia (lirik diubah jadi bahasa inggris) <br>Your eyes weaken me, When I first saw you, And honestly, <br>I never felt, I've never felt this way.'</html>",
            "string1": "Mata ke Hati",
            "string2": "Cinta Luar Biasa",
            "string3": "Dari Mata",
            "string4": "Bersamamu",
            "benar": 3
        },
        {
            "pertanyaan": "<html>'Feel the rhythm getting louder, <br>show the world what we can do' <br>Siapa penyanyinya dan apa judulnya?</html>",
            "string1": "Shakira – Waka Waka",
            "string2": "David Guetta ft. Usher – Without You",
            "string3": "K'naan – Wavin' Flag",
            "string4": "Jennifer Lopez ft. Pitbull – We Are One (Ole Ola)",
            "benar": 4
        },
        {
            "pertanyaan": "<html>'Belum ada satu bulan~' nama lengkap penyayi <br>lagu dari potongan lirik tersebut adalah</html>",
            "string1": "Bernadya Ribka Jayakusuma",
            "string2": "Bernadya JayaKusuma",
            "string3": "Bernadya Kusumawati",
            "string4": "Bernadia Riska Kusumawati",
            "benar": 1
        },
        {
            "pertanyaan": "<html>'Tempat mencari segala kebutuhan, <br>belanja puas dengan harga hemat'. <br>Jingle dari minimarket mana ini?</html>",
            "string1": "Alfamart",
            "string2": "Alfamidi",
            "string3": "Indomaret",
            "string4": "Luwes",
            "benar": 2
        },
        {
            "pertanyaan": "<html>'Nobody said it was easy' <br>apa lanjutan lirik ini?</html>",
            "string1": "It's such a shame for us to part",
            "string2": "But no one said it would be so hard",
            "string3": "I never thought I'd fall so far",
            "string4": "It's something I can't restart",
            "benar": 1
        },
        {
            "pertanyaan": "<html>'I used to rule the world, <br>seas would rise when I gave the word' <br>apa sambungan lirik tersebut?</html>",
            "string1": "And all the battles I've ever known",
            "string2": "And I hold my breath in the throne",
            "string3": "Now in the morning I sleep alone",
            "string4": "Now the world feels cold and old",
            "benar": 3
        }
    ]
}